{
  "elements": [
    {
      "element": {
        "element_type": "minecraft:single_pool_element",
        "location": "natures_spirit:village/adobe/houses/adobe_house_layer_1",
        "processors": "natures_spirit:fix_button",
        "projection": "rigid"
      },
      "weight": 1
    },
    {
      "element": {
        "element_type": "minecraft:single_pool_element",
        "location": "natures_spirit:village/adobe/houses/adobe_armorer_layer_1",
        "processors": "natures_spirit:fix_button",
        "projection": "rigid"
      },
      "weight": 2
    },
    {
      "element": {
        "element_type": "minecraft:single_pool_element",
        "location": "natures_spirit:village/adobe/houses/adobe_fletcher_layer_1",
        "processors": "natures_spirit:fix_button",
        "projection": "rigid"
      },
      "weight": 2
    },
    {
      "element": {
        "element_type": "minecraft:single_pool_element",
        "location": "natures_spirit:village/adobe/houses/adobe_library_layer_1",
        "processors": "natures_spirit:fix_button",
        "projection": "rigid"
      },
      "weight": 2
    },
    {
      "element": {
        "element_type": "minecraft:single_pool_element",
        "location": "natures_spirit:village/adobe/houses/adobe_masonry_layer_1",
        "processors": "natures_spirit:fix_button",
        "projection": "rigid"
      },
      "weight": 2
    },
    {
      "element": {
        "element_type": "minecraft:single_pool_element",
        "location": "natures_spirit:village/adobe/houses/adobe_house_2_layer_1",
        "processors": "natures_spirit:fix_button",
        "projection": "rigid"
      },
      "weight": 3
    },
    {
      "element": {
        "element_type": "minecraft:single_pool_element",
        "location": "natures_spirit:village/adobe/houses/adobe_house_3_layer_1",
        "processors": "natures_spirit:fix_button",
        "projection": "rigid"
      },
      "weight": 3
    },
    {
      "element": {
        "element_type": "minecraft:single_pool_element",
        "location": "natures_spirit:village/adobe/houses/adobe_house_4_layer_1",
        "processors": "natures_spirit:fix_button",
        "projection": "rigid"
      },
      "weight": 3
    },
    {
      "element": {
        "element_type": "minecraft:single_pool_element",
        "location": "natures_spirit:village/adobe/houses/adobe_stairs_layer_1",
        "processors": "natures_spirit:fix_button",
        "projection": "rigid"
      },
      "weight": 8
    },
    {
      "element": {
        "element_type": "minecraft:single_pool_element",
        "location": "natures_spirit:village/adobe/houses/adobe_stairs_2_layer_1",
        "processors": "natures_spirit:fix_button",
        "projection": "rigid"
      },
      "weight": 8
    },
    {
      "element": {
        "element_type": "minecraft:single_pool_element",
        "location": "natures_spirit:village/adobe/houses/adobe_set_cornor_layer_1",
        "processors": "natures_spirit:fix_button",
        "projection": "rigid"
      },
      "weight": 7
    },
    {
      "element": {
        "element_type": "minecraft:single_pool_element",
        "location": "natures_spirit:village/adobe/houses/adobe_set_cornor_2_layer_1",
        "processors": "natures_spirit:fix_button",
        "projection": "rigid"
      },
      "weight": 7
    }
  ],
  "fallback": "natures_spirit:village/adobe/side_terminators"
}